moscan/__init__.py
moscan/_core.py
moscan/models.py
moscan/migrations/__init__.py
moscan-0.0.1.dist-info/LICENSE
moscan-0.0.1.dist-info/WHEEL
moscan-0.0.1.dist-info/METADATA
moscan-0.0.1.dist-info/RECORD
