Metadata-Version: 2.3
Name: moscan
Version: 0.0.1
Summary: Model-based single-cell analytics.
Author-email: Lamin Labs <open-source@lamin.ai>
Requires-Python: >=3.9,<3.13
Requires-Dist: lamindb
Requires-Dist: pre-commit ; extra == "dev"
Requires-Dist: nox ; extra == "dev"
Requires-Dist: pytest>=6.0 ; extra == "dev"
Requires-Dist: pytest-cov ; extra == "dev"
Requires-Dist: nbproject_test ; extra == "dev"
Project-URL: Home, https://github.com/laminlabs/moscan
Provides-Extra: dev
